plum/__init__.py
plum/__version__.py
plum/clients/__init__.py
plum/clients/postgresql/__init__.py
plum/clients/postgresql/client.py
plum/clients/postgresql/connectors/__init__.py
plum/clients/postgresql/connectors/base_connector.py
plum/clients/postgresql/connectors/sql_login_connector.py
plum/clients/s3/__init__.py
plum/clients/s3/client.py
plum/clients/s3/connectors/__init__.py
plum/clients/s3/connectors/access_key_connector.py
plum/clients/s3/connectors/base_connector.py
plum/jobs/__init__.py
plum/jobs/base_job.py
plum/jobs/utils/__init__.py
plum/jobs/utils/execution/__init__.py
plum/jobs/utils/execution/recorder.py
plum_project-1.0.1.dist-info/LICENSE
plum_project-1.0.1.dist-info/METADATA
plum_project-1.0.1.dist-info/WHEEL
plum_project-1.0.1.dist-info/top_level.txt
plum_project-1.0.1.dist-info/RECORD
