Metadata-Version: 2.1
Name: plum-project
Version: 1.0.1
Summary: A python data job framework to simplify development and operations.
Keywords: data,etl,jobs
License-File: LICENSE
Requires-Dist: psycopg[binary] ==3.1.16
Requires-Dist: requests ==2.31.0
Requires-Dist: python-dotenv ==1.0.1
Requires-Dist: boto3 ==1.34.64
Requires-Dist: botocore ==1.34.64
